xml_miner/__init__.py
xml_miner/mine_trxml.py
xml_miner/mine_xml.py
xml_miner/miner.py
xml_miner/data_utils/__init__.py
xml_miner/data_utils/asclient.py
xml_miner/data_utils/data_loader.py
xml_miner/data_utils/data_saver.py
xml_miner/selectors/__init__.py
xml_miner/selectors/selector_utils.py
xml_miner/selectors/trxml_selector.py
xml_miner/selectors/trxml_selectors.py
xml_miner/selectors/xml_selector.py
xml_miner/selectors/xml_selectors.py
xml_miner/xml/__init__.py
xml_miner/xml/base_xml.py
xml_miner/xml/tk_trxml.py
xml_miner/xml/tk_xml.py
xml_miner-0.0.5.dist-info/AUTHORS.rst
xml_miner-0.0.5.dist-info/LICENSE
xml_miner-0.0.5.dist-info/METADATA
xml_miner-0.0.5.dist-info/WHEEL
xml_miner-0.0.5.dist-info/entry_points.txt
xml_miner-0.0.5.dist-info/top_level.txt
xml_miner-0.0.5.dist-info/RECORD
