Metadata-Version: 2.1
Name: xml-miner
Version: 0.0.5
Summary: data mining tool, to mine data from batch of xml files
Home-page: https://github.com/tilaboy/xml-miner
Author: Chao Li
Author-email: chaoli.job@gmail.com
License: MIT license
Keywords: data mining,xml
Platform: UNKNOWN
Classifier: Development Status :: 2 - Pre-Alpha
Classifier: Intended Audience :: Developers
Classifier: License :: OSI Approved :: MIT License
Classifier: Natural Language :: English
Classifier: Programming Language :: Python :: 3.6
Classifier: Programming Language :: Python :: 3.7
